setup.py
messenger_server_project.egg-info/PKG-INFO
messenger_server_project.egg-info/SOURCES.txt
messenger_server_project.egg-info/dependency_links.txt
messenger_server_project.egg-info/requires.txt
messenger_server_project.egg-info/top_level.txt
server/__init__.py
server/server.py
server/common/__init__.py
server/common/decor.py
server/common/descrpts.py
server/common/errors.py
server/common/metaclss.py
server/common/utils.py
server/common/variables.py
server/doc/__init__.py
server/doc/source/__init__.py
server/doc/source/conf.py
server/logs/__init__.py
server/logs/config_client_log.py
server/logs/config_server_log.py
server/project_unittests/__init__.py
server/project_unittests/test_client.py
server/project_unittests/test_server.py
server/server/__init__.py
server/server/add_user.py
server/server/config_window.py
server/server/core.py
server/server/database_server.py
server/server/delete_user.py
server/server/main_window.py
server/server/stat_window.py