Metadata-Version: 1.0
Name: messenger-server-project
Version: 0.0.2
Summary: messenger_server_project
Home-page: UNKNOWN
Author: Andrei Karachenko
Author-email: iv.iv@yandex.ru
License: UNKNOWN
Platform: UNKNOWN
